_graphspme.cp38-win_amd64.pyd
graphspme/__init__.py
GraphSPME-0.0.1.dist-info/METADATA
GraphSPME-0.0.1.dist-info/WHEEL
GraphSPME-0.0.1.dist-info/top_level.txt
GraphSPME-0.0.1.dist-info/RECORD
