Metadata-Version: 2.1
Name: GraphSPME
Version: 0.0.1
Summary: High dimensional precision matrix estimation with a known graphical structure
Home-page: https://github.com/Blunde1/GraphSPME
Author: Berent Ånund Strømnes Lunde
Author-email: lundeberent@gmail.com
License: UNKNOWN
Platform: UNKNOWN
Requires-Python: >=3.6
Requires-Dist: numpy
Requires-Dist: scipy
Provides-Extra: test
Requires-Dist: pytest ; extra == 'test'
